devine/__main__.py
devine/commands/__init__.py
devine/commands/cfg.py
devine/commands/dl.py
devine/commands/env.py
devine/commands/kv.py
devine/commands/search.py
devine/commands/serve.py
devine/commands/util.py
devine/commands/wvd.py
devine/core/__init__.py
devine/core/__main__.py
devine/core/binaries.py
devine/core/cacher.py
devine/core/commands.py
devine/core/config.py
devine/core/console.py
devine/core/constants.py
devine/core/credential.py
devine/core/downloaders/__init__.py
devine/core/downloaders/aria2c.py
devine/core/downloaders/curl_impersonate.py
devine/core/downloaders/requests.py
devine/core/drm/__init__.py
devine/core/drm/clearkey.py
devine/core/drm/widevine.py
devine/core/events.py
devine/core/manifests/__init__.py
devine/core/manifests/dash.py
devine/core/manifests/hls.py
devine/core/proxies/__init__.py
devine/core/proxies/basic.py
devine/core/proxies/hola.py
devine/core/proxies/nordvpn.py
devine/core/proxies/proxy.py
devine/core/search_result.py
devine/core/service.py
devine/core/services.py
devine/core/titles/__init__.py
devine/core/titles/episode.py
devine/core/titles/movie.py
devine/core/titles/song.py
devine/core/titles/title.py
devine/core/tracks/__init__.py
devine/core/tracks/attachment.py
devine/core/tracks/audio.py
devine/core/tracks/chapter.py
devine/core/tracks/chapters.py
devine/core/tracks/subtitle.py
devine/core/tracks/track.py
devine/core/tracks/tracks.py
devine/core/tracks/video.py
devine/core/utilities.py
devine/core/utils/__init__.py
devine/core/utils/click_types.py
devine/core/utils/collections.py
devine/core/utils/sslciphers.py
devine/core/utils/subprocess.py
devine/core/utils/webvtt.py
devine/core/utils/xml.py
devine/core/vault.py
devine/core/vaults.py
devine/vaults/API.py
devine/vaults/MySQL.py
devine/vaults/SQLite.py
devine/vaults/__init__.py
devine-3.3.3.dist-info/LICENSE
devine-3.3.3.dist-info/METADATA
devine-3.3.3.dist-info/WHEEL
devine-3.3.3.dist-info/entry_points.txt
devine-3.3.3.dist-info/RECORD
