Metadata-Version: 2.1
Name: devine
Version: 3.3.3
Summary: Modular Movie, TV, and Music Archival Software.
Home-page: https://github.com/devine-dl/devine
License: GPL-3.0-only
Keywords: python,downloader,drm,widevine
Author: rlaphoenix
Author-email: rlaphoenix@pm.me
Requires-Python: >=3.9,<4.0
Classifier: Development Status :: 4 - Beta
Classifier: Environment :: Console
Classifier: Intended Audience :: End Users/Desktop
Classifier: License :: OSI Approved :: GNU General Public License v3 (GPLv3)
Classifier: Natural Language :: English
Classifier: Operating System :: OS Independent
Classifier: Programming Language :: Python :: 3
Classifier: Programming Language :: Python :: 3.9
Classifier: Programming Language :: Python :: 3.10
Classifier: Programming Language :: Python :: 3.11
Classifier: Topic :: Multimedia :: Video
Classifier: Topic :: Security :: Cryptography
Requires-Dist: Brotli (>=1.1.0,<2.0.0)
Requires-Dist: PyYAML (>=6.0.1,<7.0.0)
Requires-Dist: Unidecode (>=1.3.8,<2.0.0)
Requires-Dist: appdirs (>=1.4.4,<2.0.0)
Requires-Dist: chardet (>=5.2.0,<6.0.0)
Requires-Dist: click (>=8.1.7,<9.0.0)
Requires-Dist: construct (>=2.8.8,<3.0.0)
Requires-Dist: crccheck (>=1.3.0,<2.0.0)
Requires-Dist: curl-cffi (>=0.7.0b4,<0.8.0)
Requires-Dist: jsonpickle (>=3.0.4,<4.0.0)
Requires-Dist: langcodes[data] (>=3.4.0,<4.0.0)
Requires-Dist: lxml (>=5.2.1,<6.0.0)
Requires-Dist: pproxy (>=2.7.9,<3.0.0)
Requires-Dist: protobuf (>=4.25.3,<5.0.0)
Requires-Dist: pycaption (>=2.2.6,<3.0.0)
Requires-Dist: pycryptodomex (>=3.20.0,<4.0.0)
Requires-Dist: pyjwt (>=2.8.0,<3.0.0)
Requires-Dist: pymediainfo (>=6.1.0,<7.0.0)
Requires-Dist: pymp4 (>=1.4.0,<2.0.0)
Requires-Dist: pymysql (>=1.1.0,<2.0.0)
Requires-Dist: pywidevine[serve] (>=1.8.0,<2.0.0)
Requires-Dist: requests[socks] (>=2.31.0,<3.0.0)
Requires-Dist: rich (>=13.7.1,<14.0.0)
Requires-Dist: rlaphoenix.m3u8 (>=3.4.0,<4.0.0)
Requires-Dist: ruamel.yaml (>=0.18.6,<0.19.0)
Requires-Dist: sortedcontainers (>=2.4.0,<3.0.0)
Requires-Dist: subtitle-filter (>=1.4.9,<2.0.0)
Requires-Dist: urllib3 (>=2.2.1,<3.0.0)
Project-URL: Changelog, https://github.com/devine-dl/devine/blob/master/CHANGELOG.md
Project-URL: Discussions, https://github.com/devine-dl/devine/discussions
Project-URL: Issues, https://github.com/devine-dl/devine/issues
Project-URL: Repository, https://github.com/devine-dl/devine
